[
  {
    "room": "Lobby",
    "id": [
      "YgXxjRN",
      "4J22S6i",
      "kesVqEA",
      "wPsLCeG",
      "VQJ7Vae",
      "k99ovZX",
      "jFowNeg"
    ],
    "agent": [],
    "navigation": { "allow": ["YgXxjRN", "4J22S6i", "kesVqEA", "wPsLCeG"] },
    "translation": { "allow": [] },
    "map": {
      "allow": ["all"],
      "image_ratio": 1,
      "scale_ratio": [0.1, 0.1]
    },
    "tutorial": {
      "allow": ["all"],
      "slides": 13,
      "position": [1.0, 2.0, 5],
      "ratio": 0.4545,
      "rotation": [0, 1.5708, 0],
      "type": "fixed"
    }
  },
  {
    "room": "Tradeshows",
    "id": ["bSwZVUz", "7mDvHxS", "jc4UGeB", "tTVCqkV"],
    "agent": ["bSwZVUz", "7mDvHxS", "jc4UGeB"],
    "translation": {
      "allow": [],
      "conversation": { "type": "bubble" },
      "spatiality": {
        "type": "borders",
        "data": [-13.0, 13.0, -12.0, 2.0]
      },
      "panel": { "type": "avatar" }
    },
    "navigation": {
      "allow": ["bSwZVUz", "7mDvHxS", "jc4UGeB"],
      "targets": [
        {
          "name": "conference room",
          "position": [26.75, 44.5]
        },
        {
          "name": "business room",
          "position": [16, 4]
        },
        {
          "name": "social area",
          "position": [5, 44.5]
        },
        { "name": "booth 1", "position": [13.5, 17.5] },
        {
          "name": "booth 2",
          "position": [13.5, 12.5]
        },
        {
          "name": "booth 3",
          "position": [4.5, 12.5]
        },
        {
          "name": "booth 4",
          "position": [4.5, 17.5]
        }
      ],
      "dimensions": [0, 30, 0, 65],
      "polygon": [
        [0.0, 65.0],
        [20.0, 65.0],
        [20.0, 60.0],
        [10.0, 60.0],
        [10.0, 47.0],
        [23.5, 47.0],
        [23.5, 29.0],
        [23.6, 29.0],
        [23.6, 47.0],
        [30.0, 47.0],
        [30.0, 0.0],
        [13.5, 0.0],
        [13.5, 8.0],
        [23.6, 8.0],
        [23.6, 24.0],
        [23.5, 24.0],
        [23.5, 8.1],
        [0.0, 8.1],
        [0.0, 22.0],
        [18.0, 22.0],
        [18.0, 42.0],
        [0.0, 42.0],
        [0.0, 65.0]
      ],
      "obstacles": [
        [
          [7, 21.5],
          [7, 18.5],
          [2, 18.5],
          [2, 21.5]
        ],
        [
          [7, 11.5],
          [7, 8.5],
          [2, 8.5],
          [2, 11.5]
        ],
        [
          [16, 21.5],
          [16, 18.5],
          [11, 18.5],
          [11, 21.5]
        ],
        [
          [16, 11.5],
          [16, 8.5],
          [11, 8.5],
          [11, 11.5]
        ]
      ]
    },
    "map": {
      "allow": ["all"],
      "file": "https://kontopoulosdm.github.io/tradeshows_map.png",
      "ratio": 1.1,
      "mapToImage": [0.869, 0.91],
      "roomLength": [35, 40],
      "center": [0, -0.0435],
      "centeroffset": [0, 20]
    },
    "tutorial": {
      "allow": ["all"],
      "slides": 4,
      "position": [0, 0, -1],
      "rotation": [0, 0, 0],
      "ratio": 0.4545,
      "type": "moving"
    }
  },
  {
    "room": "Conference Room",
    "id": ["bQ4vf2n", "AxFm4cE"],
    "agent": [],
    "navigation": { "allow": [] },
    "translation": {
      "allow": ["all"],
      "conversation": {
        "type": "presentation",
        "data": [4.0, 16.0, -20.0, -15.2]
      },
      "spatiality": { "type": "room" },
      "panel": { "type": "fixed", "data": [10, 7.5, -21.3] }
    },
    "map": { "allow": [] },
    "tutorial": {
      "allow": ["all"],
      "slides": 2,
      "position": [0, 0, -1],
      "rotation": [0, 0, 0],
      "ratio": 0.4545,
      "type": "moving"
    }
  },
  {
    "room": "Business Room",
    "id": [],
    "agent": [],
    "navigation": { "allow": ["all"] },
    "translation": {
      "allow": ["all"],
      "conversation": { "type": "duo" },
      "spatiality": { "type": "room" },
      "panel": { "type": "fixed", "data": [1, 2, 3] }
    },
    "map": { "allow": [] },
    "tutorial": { "allow": [] }
  }
]
